[
  {
    "id": "galloway-absegami",
    "name": "Absegami",
    "slug": "galloway-absegami"
  },
  {
    "id": "allentown-allentown",
    "name": "Allentown",
    "slug": "allentown-allentown"
  },
  {
    "id": "asbury-park-asbury-park",
    "name": "Asbury Park",
    "slug": "asbury-park-asbury-park"
  },
  {
    "id": "atlantic-city-atlantic-city",
    "name": "Atlantic City",
    "slug": "atlantic-city-atlantic-city"
  },
  {
    "id": "audubon-audubon",
    "name": "Audubon",
    "slug": "audubon-audubon"
  },
  {
    "id": "barnegat-barnegat",
    "name": "Barnegat",
    "slug": "barnegat-barnegat"
  },
  {
    "id": "newark-barringer",
    "name": "Barringer",
    "slug": "newark-barringer"
  },
  {
    "id": "bayonne-bayonne",
    "name": "Bayonne",
    "slug": "bayonne-bayonne"
  },
  {
    "id": "east-rutherford-becton",
    "name": "Becton",
    "slug": "east-rutherford-becton"
  },
  {
    "id": "belleville-belleville",
    "name": "Belleville",
    "slug": "belleville-belleville"
  },
  {
    "id": "belvidere-belvidere",
    "name": "Belvidere",
    "slug": "belvidere-belvidere"
  },
  {
    "id": "oradell-bergen-catholic",
    "name": "Bergen Catholic",
    "slug": "oradell-bergen-catholic"
  },
  {
    "id": "teterboro-bergen-charter",
    "name": "Bergen Charter",
    "slug": "teterboro-bergen-charter"
  },
  {
    "id": "bergenfield-bergenfield",
    "name": "Bergenfield",
    "slug": "bergenfield-bergenfield"
  },
  {
    "id": "bernardsville-bernards",
    "name": "Bernards",
    "slug": "bernardsville-bernards"
  },
  {
    "id": "blairstown-blair",
    "name": "Blair",
    "slug": "blairstown-blair"
  },
  {
    "id": "bloomfield-bloomfield",
    "name": "Bloomfield",
    "slug": "bloomfield-bloomfield"
  },
  {
    "id": "boonton-boonton",
    "name": "Boonton",
    "slug": "boonton-boonton"
  },
  {
    "id": "bordentown-bordentown",
    "name": "Bordentown",
    "slug": "bordentown-bordentown"
  },
  {
    "id": "bound-brook-bound-brook",
    "name": "Bound Brook",
    "slug": "bound-brook-bound-brook"
  },
  {
    "id": "kenilworth-brearley",
    "name": "Brearley",
    "slug": "kenilworth-brearley"
  },
  {
    "id": "brick-brick-memorial",
    "name": "Brick Memorial",
    "slug": "brick-brick-memorial"
  },
  {
    "id": "brick-brick-township",
    "name": "Brick Township",
    "slug": "brick-brick-township"
  },
  {
    "id": "bridgewater-bridgewater-raritan",
    "name": "Bridgewater-Raritan",
    "slug": "bridgewater-bridgewater-raritan"
  },
  {
    "id": "buena-buena",
    "name": "Buena",
    "slug": "buena-buena"
  },
  {
    "id": "burlington-burlington-city",
    "name": "Burlington City",
    "slug": "burlington-burlington-city"
  },
  {
    "id": "burlington-twp-burlington-township",
    "name": "Burlington Township",
    "slug": "burlington-twp-burlington-township"
  },
  {
    "id": "butler-butler",
    "name": "Butler",
    "slug": "butler-butler"
  },
  {
    "id": "west-caldwell-caldwell",
    "name": "Caldwell",
    "slug": "west-caldwell-caldwell"
  },
  {
    "id": "camden-camden",
    "name": "Camden",
    "slug": "camden-camden"
  },
  {
    "id": "cherry-hill-camden-catholic",
    "name": "Camden Catholic",
    "slug": "cherry-hill-camden-catholic"
  },
  {
    "id": "carteret-carteret",
    "name": "Carteret",
    "slug": "carteret-carteret"
  },
  {
    "id": "egg-harbor-city-cedar-creek",
    "name": "Cedar Creek",
    "slug": "egg-harbor-city-cedar-creek"
  },
  {
    "id": "cedar-grove-cedar-grove",
    "name": "Cedar Grove",
    "slug": "cedar-grove-cedar-grove"
  },
  {
    "id": "somerset-central-jersey-college-charter",
    "name": "Central Jersey College Charter",
    "slug": "somerset-central-jersey-college-charter"
  },
  {
    "id": "bayville-central-regional",
    "name": "Central Regional",
    "slug": "bayville-central-regional"
  },
  {
    "id": "marlton-cherokee",
    "name": "Cherokee",
    "slug": "marlton-cherokee"
  },
  {
    "id": "cherry-hill-cherry-hill-east",
    "name": "Cherry Hill East",
    "slug": "cherry-hill-cherry-hill-east"
  },
  {
    "id": "cherry-hill-cherry-hill-west",
    "name": "Cherry Hill West",
    "slug": "cherry-hill-cherry-hill-west"
  },
  {
    "id": "lincroft-christian-brothers",
    "name": "Christian Brothers",
    "slug": "lincroft-christian-brothers"
  },
  {
    "id": "cinnaminson-cinnaminson",
    "name": "Cinnaminson",
    "slug": "cinnaminson-cinnaminson"
  },
  {
    "id": "clayton-clayton",
    "name": "Clayton",
    "slug": "clayton-clayton"
  },
  {
    "id": "mullica-hill-clearview",
    "name": "Clearview",
    "slug": "mullica-hill-clearview"
  },
  {
    "id": "cliffside-park-cliffside-park",
    "name": "Cliffside Park",
    "slug": "cliffside-park-cliffside-park"
  },
  {
    "id": "clifton-clifton",
    "name": "Clifton",
    "slug": "clifton-clifton"
  },
  {
    "id": "paterson-college-achieve-paterson",
    "name": "College Achieve Paterson",
    "slug": "paterson-college-achieve-paterson"
  },
  {
    "id": "collingswood-collingswood",
    "name": "Collingswood",
    "slug": "collingswood-collingswood"
  },
  {
    "id": "colonia-colonia",
    "name": "Colonia",
    "slug": "colonia-colonia"
  },
  {
    "id": "colts-neck-colts-neck",
    "name": "Colts Neck",
    "slug": "colts-neck-colts-neck"
  },
  {
    "id": "maplewood-columbia",
    "name": "Columbia",
    "slug": "maplewood-columbia"
  },
  {
    "id": "cranford-cranford",
    "name": "Cranford",
    "slug": "cranford-cranford"
  },
  {
    "id": "cresskill-cresskill",
    "name": "Cresskill",
    "slug": "cresskill-cresskill"
  },
  {
    "id": "seabrook-cumberland",
    "name": "Cumberland",
    "slug": "seabrook-cumberland"
  },
  {
    "id": "wayne-depaul",
    "name": "DePaul",
    "slug": "wayne-depaul"
  },
  {
    "id": "alexandria-delaware-valley",
    "name": "Delaware Valley",
    "slug": "alexandria-delaware-valley"
  },
  {
    "id": "morristown-delbarton",
    "name": "Delbarton",
    "slug": "morristown-delbarton"
  },
  {
    "id": "delran-delran",
    "name": "Delran",
    "slug": "delran-delran"
  },
  {
    "id": "franklinville-delsea",
    "name": "Delsea",
    "slug": "franklinville-delsea"
  },
  {
    "id": "demarest-demarest",
    "name": "Demarest",
    "slug": "demarest-demarest"
  },
  {
    "id": "deptford-deptford",
    "name": "Deptford",
    "slug": "deptford-deptford"
  },
  {
    "id": "ramsey-don-bosco-prep",
    "name": "Don Bosco Prep",
    "slug": "ramsey-don-bosco-prep"
  },
  {
    "id": "toms-river-donovan-catholic",
    "name": "Donovan Catholic",
    "slug": "toms-river-donovan-catholic"
  },
  {
    "id": "dover-dover",
    "name": "Dover",
    "slug": "dover-dover"
  },
  {
    "id": "dumont-dumont",
    "name": "Dumont",
    "slug": "dumont-dumont"
  },
  {
    "id": "englewood-dwight-morrow",
    "name": "Dwight-Morrow",
    "slug": "englewood-dwight-morrow"
  },
  {
    "id": "east-brunswick-east-brunswick",
    "name": "East Brunswick",
    "slug": "east-brunswick-east-brunswick"
  },
  {
    "id": "east-orange-east-orange",
    "name": "East Orange",
    "slug": "east-orange-east-orange"
  },
  {
    "id": "voorhees-eastern",
    "name": "Eastern",
    "slug": "voorhees-eastern"
  },
  {
    "id": "edison-edison",
    "name": "Edison",
    "slug": "edison-edison"
  },
  {
    "id": "egg-harbor-twp-egg-harbor",
    "name": "Egg Harbor",
    "slug": "egg-harbor-twp-egg-harbor"
  },
  {
    "id": "elizabeth-elizabeth",
    "name": "Elizabeth",
    "slug": "elizabeth-elizabeth"
  },
  {
    "id": "elmwood-park-elmwood-park",
    "name": "Elmwood Park",
    "slug": "elmwood-park-elmwood-park"
  },
  {
    "id": "emerson-emerson-boro",
    "name": "Emerson Boro",
    "slug": "emerson-emerson-boro"
  },
  {
    "id": "ewing-ewing",
    "name": "Ewing",
    "slug": "ewing-ewing"
  },
  {
    "id": "fair-lawn-fair-lawn",
    "name": "Fair Lawn",
    "slug": "fair-lawn-fair-lawn"
  },
  {
    "id": "fort-lee-fort-lee",
    "name": "Fort Lee",
    "slug": "fort-lee-fort-lee"
  },
  {
    "id": "somerset-franklin",
    "name": "Franklin",
    "slug": "somerset-franklin"
  },
  {
    "id": "freehold-freehold-borough",
    "name": "Freehold Borough",
    "slug": "freehold-freehold-borough"
  },
  {
    "id": "freehold-freehold-township",
    "name": "Freehold Township",
    "slug": "freehold-freehold-township"
  },
  {
    "id": "garfield-garfield",
    "name": "Garfield",
    "slug": "garfield-garfield"
  },
  {
    "id": "woodbury-hts-gateway",
    "name": "Gateway",
    "slug": "woodbury-hts-gateway"
  },
  {
    "id": "glen-ridge-glen-ridge",
    "name": "Glen Ridge",
    "slug": "glen-ridge-glen-ridge"
  },
  {
    "id": "glen-rock-glen-rock",
    "name": "Glen Rock",
    "slug": "glen-rock-glen-rock"
  },
  {
    "id": "gloucester-city-gloucester",
    "name": "Gloucester",
    "slug": "gloucester-city-gloucester"
  },
  {
    "id": "gloucester-city-gloucester-catholic",
    "name": "Gloucester Catholic",
    "slug": "gloucester-city-gloucester-catholic"
  },
  {
    "id": "berkeley-hts-gov-livingston",
    "name": "Gov. Livingston",
    "slug": "berkeley-hts-gov-livingston"
  },
  {
    "id": "hackensack-hackensack",
    "name": "Hackensack",
    "slug": "hackensack-hackensack"
  },
  {
    "id": "hackettstown-hackettstown",
    "name": "Hackettstown",
    "slug": "hackettstown-hackettstown"
  },
  {
    "id": "haddon-heights-haddon-heights",
    "name": "Haddon Heights",
    "slug": "haddon-heights-haddon-heights"
  },
  {
    "id": "westmont-haddon-township",
    "name": "Haddon Township",
    "slug": "westmont-haddon-township"
  },
  {
    "id": "haddonfield-haddonfield",
    "name": "Haddonfield",
    "slug": "haddonfield-haddonfield"
  },
  {
    "id": "hamilton-hamilton-west",
    "name": "Hamilton West",
    "slug": "hamilton-hamilton-west"
  },
  {
    "id": "hammonton-hammonton",
    "name": "Hammonton",
    "slug": "hammonton-hammonton"
  },
  {
    "id": "east-hanover-hanover-park",
    "name": "Hanover Park",
    "slug": "east-hanover-hanover-park"
  },
  {
    "id": "hasbrouck-hts-hasbrouck-heights",
    "name": "Hasbrouck Heights",
    "slug": "hasbrouck-hts-hasbrouck-heights"
  },
  {
    "id": "hawthorne-hawthorne",
    "name": "Hawthorne",
    "slug": "hawthorne-hawthorne"
  },
  {
    "id": "sussex-high-point",
    "name": "High Point",
    "slug": "sussex-high-point"
  },
  {
    "id": "blackwood-highland",
    "name": "Highland",
    "slug": "blackwood-highland"
  },
  {
    "id": "highland-park-highland-park",
    "name": "Highland Park",
    "slug": "highland-park-highland-park"
  },
  {
    "id": "hightstown-hightstown",
    "name": "Hightstown",
    "slug": "hightstown-hightstown"
  },
  {
    "id": "hillsborough-hillsborough",
    "name": "Hillsborough",
    "slug": "hillsborough-hillsborough"
  },
  {
    "id": "hillside-hillside",
    "name": "Hillside",
    "slug": "hillside-hillside"
  },
  {
    "id": "hoboken-hoboken",
    "name": "Hoboken",
    "slug": "hoboken-hoboken"
  },
  {
    "id": "holmdel-holmdel",
    "name": "Holmdel",
    "slug": "holmdel-holmdel"
  },
  {
    "id": "delran-holy-cross-prep",
    "name": "Holy Cross Prep",
    "slug": "delran-holy-cross-prep"
  },
  {
    "id": "absecon-holy-spirit",
    "name": "Holy Spirit",
    "slug": "absecon-holy-spirit"
  },
  {
    "id": "pennington-hopewell-valley",
    "name": "Hopewell Valley",
    "slug": "pennington-hopewell-valley"
  },
  {
    "id": "farmingdale-howell",
    "name": "Howell",
    "slug": "farmingdale-howell"
  },
  {
    "id": "flemington-hunterdon-central",
    "name": "Hunterdon Central",
    "slug": "flemington-hunterdon-central"
  },
  {
    "id": "somerville-immaculata",
    "name": "Immaculata",
    "slug": "somerville-immaculata"
  },
  {
    "id": "oakland-indian-hills",
    "name": "Indian Hills",
    "slug": "oakland-indian-hills"
  },
  {
    "id": "irvington-irvington",
    "name": "Irvington",
    "slug": "irvington-irvington"
  },
  {
    "id": "iselin-iselin-kennedy",
    "name": "Iselin Kennedy",
    "slug": "iselin-iselin-kennedy"
  },
  {
    "id": "edison-jp-stevens",
    "name": "J.P. Stevens",
    "slug": "edison-jp-stevens"
  },
  {
    "id": "jackson-jackson-township",
    "name": "Jackson Township",
    "slug": "jackson-jackson-township"
  },
  {
    "id": "oak-ridge-jefferson",
    "name": "Jefferson",
    "slug": "oak-ridge-jefferson"
  },
  {
    "id": "clark-johnson",
    "name": "Johnson",
    "slug": "clark-johnson"
  },
  {
    "id": "keansburg-keansburg",
    "name": "Keansburg",
    "slug": "keansburg-keansburg"
  },
  {
    "id": "kearny-kearny",
    "name": "Kearny",
    "slug": "kearny-kearny"
  },
  {
    "id": "keyport-keyport",
    "name": "Keyport",
    "slug": "keyport-keyport"
  },
  {
    "id": "woolwich-twp-kingsway",
    "name": "Kingsway",
    "slug": "woolwich-twp-kingsway"
  },
  {
    "id": "kinnelon-kinnelon",
    "name": "Kinnelon",
    "slug": "kinnelon-kinnelon"
  },
  {
    "id": "newton-kittatinny",
    "name": "Kittatinny",
    "slug": "newton-kittatinny"
  },
  {
    "id": "livingston-kushner",
    "name": "Kushner",
    "slug": "livingston-kushner"
  },
  {
    "id": "lanoka-harbor-lacey",
    "name": "Lacey",
    "slug": "lanoka-harbor-lacey"
  },
  {
    "id": "wanaque-lakeland",
    "name": "Lakeland",
    "slug": "wanaque-lakeland"
  },
  {
    "id": "lakewood-lakewood",
    "name": "Lakewood",
    "slug": "lakewood-lakewood"
  },
  {
    "id": "lawrenceville-lawrence",
    "name": "Lawrence",
    "slug": "lawrenceville-lawrence"
  },
  {
    "id": "lawrenceville-lawrenceville",
    "name": "Lawrenceville",
    "slug": "lawrenceville-lawrenceville"
  },
  {
    "id": "medford-lenape",
    "name": "Lenape",
    "slug": "medford-lenape"
  },
  {
    "id": "stanhope-lenape-valley",
    "name": "Lenape Valley",
    "slug": "stanhope-lenape-valley"
  },
  {
    "id": "leonia-leonia",
    "name": "Leonia",
    "slug": "leonia-leonia"
  },
  {
    "id": "linden-linden",
    "name": "Linden",
    "slug": "linden-linden"
  },
  {
    "id": "lindenwold-lindenwold",
    "name": "Lindenwold",
    "slug": "lindenwold-lindenwold"
  },
  {
    "id": "livingston-livingston",
    "name": "Livingston",
    "slug": "livingston-livingston"
  },
  {
    "id": "lodi-lodi",
    "name": "Lodi",
    "slug": "lodi-lodi"
  },
  {
    "id": "long-branch-long-branch",
    "name": "Long Branch",
    "slug": "long-branch-long-branch"
  },
  {
    "id": "erma-lower-cape-may",
    "name": "Lower Cape May",
    "slug": "erma-lower-cape-may"
  },
  {
    "id": "lyndhurst-lyndhurst",
    "name": "Lyndhurst",
    "slug": "lyndhurst-lyndhurst"
  },
  {
    "id": "madison-madison",
    "name": "Madison",
    "slug": "madison-madison"
  },
  {
    "id": "mahwah-mahwah",
    "name": "Mahwah",
    "slug": "mahwah-mahwah"
  },
  {
    "id": "linwood-mainland",
    "name": "Mainland",
    "slug": "linwood-mainland"
  },
  {
    "id": "manalapan-manalapan",
    "name": "Manalapan",
    "slug": "manalapan-manalapan"
  },
  {
    "id": "manasquan-manasquan",
    "name": "Manasquan",
    "slug": "manasquan-manasquan"
  },
  {
    "id": "haledon-manchester-regional",
    "name": "Manchester Regional",
    "slug": "haledon-manchester-regional"
  },
  {
    "id": "manchester-manchester-township",
    "name": "Manchester Township",
    "slug": "manchester-manchester-township"
  },
  {
    "id": "manville-manville",
    "name": "Manville",
    "slug": "manville-manville"
  },
  {
    "id": "maple-shade-maple-shade",
    "name": "Maple Shade",
    "slug": "maple-shade-maple-shade"
  },
  {
    "id": "marlboro-marlboro",
    "name": "Marlboro",
    "slug": "marlboro-marlboro"
  },
  {
    "id": "aberdeen-matawan",
    "name": "Matawan",
    "slug": "aberdeen-matawan"
  },
  {
    "id": "mendham-mendham",
    "name": "Mendham",
    "slug": "mendham-mendham"
  },
  {
    "id": "metuchen-metuchen",
    "name": "Metuchen",
    "slug": "metuchen-metuchen"
  },
  {
    "id": "cape-may-ct-hse-middle-township",
    "name": "Middle Township",
    "slug": "cape-may-ct-hse-middle-township"
  },
  {
    "id": "middlesex-middlesex",
    "name": "Middlesex",
    "slug": "middlesex-middlesex"
  },
  {
    "id": "middletown-middletown-north",
    "name": "Middletown North",
    "slug": "middletown-middletown-north"
  },
  {
    "id": "middletown-middletown-south",
    "name": "Middletown South",
    "slug": "middletown-middletown-south"
  },
  {
    "id": "millburn-millburn",
    "name": "Millburn",
    "slug": "millburn-millburn"
  },
  {
    "id": "millville-millville",
    "name": "Millville",
    "slug": "millville-millville"
  },
  {
    "id": "tinton-falls-monmouth",
    "name": "Monmouth",
    "slug": "tinton-falls-monmouth"
  },
  {
    "id": "monroe-twp-monroe",
    "name": "Monroe",
    "slug": "monroe-twp-monroe"
  },
  {
    "id": "montclair-montclair",
    "name": "Montclair",
    "slug": "montclair-montclair"
  },
  {
    "id": "skillman-montgomery",
    "name": "Montgomery",
    "slug": "skillman-montgomery"
  },
  {
    "id": "montville-montville",
    "name": "Montville",
    "slug": "montville-montville"
  },
  {
    "id": "moorestown-moorestown",
    "name": "Moorestown",
    "slug": "moorestown-moorestown"
  },
  {
    "id": "rockaway-morris-hills",
    "name": "Morris Hills",
    "slug": "rockaway-morris-hills"
  },
  {
    "id": "rockaway-morris-knolls",
    "name": "Morris Knolls",
    "slug": "rockaway-morris-knolls"
  },
  {
    "id": "morristown-morristown",
    "name": "Morristown",
    "slug": "morristown-morristown"
  },
  {
    "id": "flanders-mount-olive",
    "name": "Mount Olive",
    "slug": "flanders-mount-olive"
  },
  {
    "id": "mountain-lakes-mountain-lakes",
    "name": "Mountain Lakes",
    "slug": "mountain-lakes-mountain-lakes"
  },
  {
    "id": "neptune-neptune",
    "name": "Neptune",
    "slug": "neptune-neptune"
  },
  {
    "id": "new-brunswick-new-brunswick",
    "name": "New Brunswick",
    "slug": "new-brunswick-new-brunswick"
  },
  {
    "id": "new-egypt-new-egypt",
    "name": "New Egypt",
    "slug": "new-egypt-new-egypt"
  },
  {
    "id": "new-milford-new-milford",
    "name": "New Milford",
    "slug": "new-milford-new-milford"
  },
  {
    "id": "new-providence-new-providence",
    "name": "New Providence",
    "slug": "new-providence-new-providence"
  },
  {
    "id": "livingston-newark-academy",
    "name": "Newark Academy",
    "slug": "livingston-newark-academy"
  },
  {
    "id": "newark-newark-collegiate",
    "name": "Newark Collegiate",
    "slug": "newark-newark-collegiate"
  },
  {
    "id": "newark-newark-east-side",
    "name": "Newark East Side",
    "slug": "newark-newark-east-side"
  },
  {
    "id": "newton-newton",
    "name": "Newton",
    "slug": "newton-newton"
  },
  {
    "id": "north-bergen-north-bergen",
    "name": "North Bergen",
    "slug": "north-bergen-north-bergen"
  },
  {
    "id": "north-brunswick-north-brunswick",
    "name": "North Brunswick",
    "slug": "north-brunswick-north-brunswick"
  },
  {
    "id": "annandale-north-hunterdon",
    "name": "North Hunterdon",
    "slug": "annandale-north-hunterdon"
  },
  {
    "id": "no-plainfield-north-plainfield",
    "name": "North Plainfield",
    "slug": "no-plainfield-north-plainfield"
  },
  {
    "id": "newark-north-star-academy",
    "name": "North Star Academy",
    "slug": "newark-north-star-academy"
  },
  {
    "id": "blairstown-north-warren",
    "name": "North Warren",
    "slug": "blairstown-north-warren"
  },
  {
    "id": "columbus-northern-burlington",
    "name": "Northern Burlington",
    "slug": "columbus-northern-burlington"
  },
  {
    "id": "allendale-northern-highlands",
    "name": "Northern Highlands",
    "slug": "allendale-northern-highlands"
  },
  {
    "id": "lawrenceville-notre-dame",
    "name": "Notre Dame",
    "slug": "lawrenceville-notre-dame"
  },
  {
    "id": "hamilton-nottingham",
    "name": "Nottingham",
    "slug": "hamilton-nottingham"
  },
  {
    "id": "nutley-nutley",
    "name": "Nutley",
    "slug": "nutley-nutley"
  },
  {
    "id": "mays-landing-oakcrest",
    "name": "Oakcrest",
    "slug": "mays-landing-oakcrest"
  },
  {
    "id": "ocean-city-ocean-city",
    "name": "Ocean City",
    "slug": "ocean-city-ocean-city"
  },
  {
    "id": "oakhurst-ocean-township",
    "name": "Ocean Township",
    "slug": "oakhurst-ocean-township"
  },
  {
    "id": "matawan-old-bridge",
    "name": "Old Bridge",
    "slug": "matawan-old-bridge"
  },
  {
    "id": "old-tappan-old-tappan",
    "name": "Old Tappan",
    "slug": "old-tappan-old-tappan"
  },
  {
    "id": "orange-orange",
    "name": "Orange",
    "slug": "orange-orange"
  },
  {
    "id": "pine-hill-overbrook",
    "name": "Overbrook",
    "slug": "pine-hill-overbrook"
  },
  {
    "id": "palmyra-palmyra",
    "name": "Palmyra",
    "slug": "palmyra-palmyra"
  },
  {
    "id": "paramus-paramus",
    "name": "Paramus",
    "slug": "paramus-paramus"
  },
  {
    "id": "paramus-paramus-catholic",
    "name": "Paramus Catholic",
    "slug": "paramus-paramus-catholic"
  },
  {
    "id": "parsippany-parsippany",
    "name": "Parsippany",
    "slug": "parsippany-parsippany"
  },
  {
    "id": "morris-plains-parsippany-hills",
    "name": "Parsippany Hills",
    "slug": "morris-plains-parsippany-hills"
  },
  {
    "id": "montvale-pascack-hills",
    "name": "Pascack Hills",
    "slug": "montvale-pascack-hills"
  },
  {
    "id": "hillsdale-pascack-valley",
    "name": "Pascack Valley",
    "slug": "hillsdale-pascack-valley"
  },
  {
    "id": "passaic-passaic",
    "name": "Passaic",
    "slug": "passaic-passaic"
  },
  {
    "id": "wayne-passaic-tech",
    "name": "Passaic Tech",
    "slug": "wayne-passaic-tech"
  },
  {
    "id": "little-falls-passaic-valley",
    "name": "Passaic Valley",
    "slug": "little-falls-passaic-valley"
  },
  {
    "id": "paterson-paterson-eastside",
    "name": "Paterson Eastside",
    "slug": "paterson-paterson-eastside"
  },
  {
    "id": "paterson-paterson-kennedy",
    "name": "Paterson Kennedy",
    "slug": "paterson-paterson-kennedy"
  },
  {
    "id": "haddonfield-paul-vi",
    "name": "Paul VI",
    "slug": "haddonfield-paul-vi"
  },
  {
    "id": "paulsboro-paulsboro",
    "name": "Paulsboro",
    "slug": "paulsboro-paulsboro"
  },
  {
    "id": "hightstown-peddie",
    "name": "Peddie",
    "slug": "hightstown-peddie"
  },
  {
    "id": "pemberton-pemberton",
    "name": "Pemberton",
    "slug": "pemberton-pemberton"
  },
  {
    "id": "carneys-point-penns-grove",
    "name": "Penns Grove",
    "slug": "carneys-point-penns-grove"
  },
  {
    "id": "pennsauken-pennsauken",
    "name": "Pennsauken",
    "slug": "pennsauken-pennsauken"
  },
  {
    "id": "pennsville-pennsville",
    "name": "Pennsville",
    "slug": "pennsville-pennsville"
  },
  {
    "id": "pompton-plains-pequannock",
    "name": "Pequannock",
    "slug": "pompton-plains-pequannock"
  },
  {
    "id": "perth-amboy-perth-amboy",
    "name": "Perth Amboy",
    "slug": "perth-amboy-perth-amboy"
  },
  {
    "id": "phillipsburg-phillipsburg",
    "name": "Phillipsburg",
    "slug": "phillipsburg-phillipsburg"
  },
  {
    "id": "tuckerton-pinelands",
    "name": "Pinelands",
    "slug": "tuckerton-pinelands"
  },
  {
    "id": "martinsville-pingry",
    "name": "Pingry",
    "slug": "martinsville-pingry"
  },
  {
    "id": "clifton-pioneer-academy",
    "name": "Pioneer Academy",
    "slug": "clifton-pioneer-academy"
  },
  {
    "id": "piscataway-piscataway",
    "name": "Piscataway",
    "slug": "piscataway-piscataway"
  },
  {
    "id": "pitman-pitman",
    "name": "Pitman",
    "slug": "pitman-pitman"
  },
  {
    "id": "plainfield-plainfield",
    "name": "Plainfield",
    "slug": "plainfield-plainfield"
  },
  {
    "id": "pt-pleasant-bch-point-pleasant-beach",
    "name": "Point Pleasant Beach",
    "slug": "pt-pleasant-bch-point-pleasant-beach"
  },
  {
    "id": "pt-pleasant-point-pleasant-boro",
    "name": "Point Pleasant Boro",
    "slug": "pt-pleasant-point-pleasant-boro"
  },
  {
    "id": "pompton-lakes-pompton-lakes",
    "name": "Pompton Lakes",
    "slug": "pompton-lakes-pompton-lakes"
  },
  {
    "id": "sparta-pope-john",
    "name": "Pope John",
    "slug": "sparta-pope-john"
  },
  {
    "id": "princeton-princeton",
    "name": "Princeton",
    "slug": "princeton-princeton"
  },
  {
    "id": "rahway-rahway",
    "name": "Rahway",
    "slug": "rahway-rahway"
  },
  {
    "id": "franklin-lakes-ramapo",
    "name": "Ramapo",
    "slug": "franklin-lakes-ramapo"
  },
  {
    "id": "ramsey-ramsey",
    "name": "Ramsey",
    "slug": "ramsey-ramsey"
  },
  {
    "id": "mount-holly-rancocas-valley",
    "name": "Rancocas Valley",
    "slug": "mount-holly-rancocas-valley"
  },
  {
    "id": "randolph-randolph",
    "name": "Randolph",
    "slug": "randolph-randolph"
  },
  {
    "id": "hazlet-raritan",
    "name": "Raritan",
    "slug": "hazlet-raritan"
  },
  {
    "id": "red-bank-red-bank-catholic",
    "name": "Red Bank Catholic",
    "slug": "red-bank-red-bank-catholic"
  },
  {
    "id": "little-silver-red-bank-regional",
    "name": "Red Bank Regional",
    "slug": "little-silver-red-bank-regional"
  },
  {
    "id": "basking-ridge-ridge",
    "name": "Ridge",
    "slug": "basking-ridge-ridge"
  },
  {
    "id": "ridgefield-ridgefield",
    "name": "Ridgefield",
    "slug": "ridgefield-ridgefield"
  },
  {
    "id": "ridgefield-park-ridgefield-park",
    "name": "Ridgefield Park",
    "slug": "ridgefield-park-ridgefield-park"
  },
  {
    "id": "ridgewood-ridgewood",
    "name": "Ridgewood",
    "slug": "ridgewood-ridgewood"
  },
  {
    "id": "oradell-river-dell",
    "name": "River Dell",
    "slug": "oradell-river-dell"
  },
  {
    "id": "riverside-riverside",
    "name": "Riverside",
    "slug": "riverside-riverside"
  },
  {
    "id": "robbinsville-robbinsville",
    "name": "Robbinsville",
    "slug": "robbinsville-robbinsville"
  },
  {
    "id": "roselle-roselle",
    "name": "Roselle",
    "slug": "roselle-roselle"
  },
  {
    "id": "roselle-park-roselle-park",
    "name": "Roselle Park",
    "slug": "roselle-park-roselle-park"
  },
  {
    "id": "succasunna-roxbury",
    "name": "Roxbury",
    "slug": "succasunna-roxbury"
  },
  {
    "id": "rumson-rumson-fair-haven",
    "name": "Rumson-Fair Haven",
    "slug": "rumson-rumson-fair-haven"
  },
  {
    "id": "somerset-rutgers-prep",
    "name": "Rutgers Prep",
    "slug": "somerset-rutgers-prep"
  },
  {
    "id": "rutherford-rutherford",
    "name": "Rutherford",
    "slug": "rutherford-rutherford"
  },
  {
    "id": "saddle-brook-saddle-brook",
    "name": "Saddle Brook",
    "slug": "saddle-brook-saddle-brook"
  },
  {
    "id": "saddle-river-saddle-river-day",
    "name": "Saddle River Day",
    "slug": "saddle-river-saddle-river-day"
  },
  {
    "id": "salem-salem",
    "name": "Salem",
    "slug": "salem-salem"
  },
  {
    "id": "parlin-sayreville",
    "name": "Sayreville",
    "slug": "parlin-sayreville"
  },
  {
    "id": "pittsgrove-schalick",
    "name": "Schalick",
    "slug": "pittsgrove-schalick"
  },
  {
    "id": "scotch-plains-scotch-plains-fanwood",
    "name": "Scotch Plains-Fanwood",
    "slug": "scotch-plains-scotch-plains-fanwood"
  },
  {
    "id": "secaucus-secaucus",
    "name": "Secaucus",
    "slug": "secaucus-secaucus"
  },
  {
    "id": "tabernacle-seneca",
    "name": "Seneca",
    "slug": "tabernacle-seneca"
  },
  {
    "id": "west-orange-seton-hall-prep",
    "name": "Seton Hall Prep",
    "slug": "west-orange-seton-hall-prep"
  },
  {
    "id": "medford-shawnee",
    "name": "Shawnee",
    "slug": "medford-shawnee"
  },
  {
    "id": "w-long-branch-shore",
    "name": "Shore",
    "slug": "w-long-branch-shore"
  },
  {
    "id": "somerville-somerville",
    "name": "Somerville",
    "slug": "somerville-somerville"
  },
  {
    "id": "monmouth-jct-south-brunswick",
    "name": "South Brunswick",
    "slug": "monmouth-jct-south-brunswick"
  },
  {
    "id": "lambertville-south-hunterdon",
    "name": "South Hunterdon",
    "slug": "lambertville-south-hunterdon"
  },
  {
    "id": "so-plainfield-south-plainfield",
    "name": "South Plainfield",
    "slug": "so-plainfield-south-plainfield"
  },
  {
    "id": "south-river-south-river",
    "name": "South River",
    "slug": "south-river-south-river"
  },
  {
    "id": "manahawkin-southern",
    "name": "Southern",
    "slug": "manahawkin-southern"
  },
  {
    "id": "sparta-sparta",
    "name": "Sparta",
    "slug": "sparta-sparta"
  },
  {
    "id": "spotswood-spotswood",
    "name": "Spotswood",
    "slug": "spotswood-spotswood"
  },
  {
    "id": "richland-st-augustine",
    "name": "St. Augustine",
    "slug": "richland-st-augustine"
  },
  {
    "id": "newark-st-benedicts",
    "name": "St. Benedict's",
    "slug": "newark-st-benedicts"
  },
  {
    "id": "holmdel-st-john-vianney",
    "name": "St. John Vianney",
    "slug": "holmdel-st-john-vianney"
  },
  {
    "id": "hammonton-st-joseph-hamm",
    "name": "St. Joseph (Hamm.)",
    "slug": "hammonton-st-joseph-hamm"
  },
  {
    "id": "metuchen-st-joseph-met",
    "name": "St. Joseph (Met.)",
    "slug": "metuchen-st-joseph-met"
  },
  {
    "id": "montvale-st-joseph-mont",
    "name": "St. Joseph (Mont.)",
    "slug": "montvale-st-joseph-mont"
  },
  {
    "id": "rutherford-st-mary-ruth",
    "name": "St. Mary (Ruth.)",
    "slug": "rutherford-st-mary-ruth"
  },
  {
    "id": "jersey-city-st-peters-prep",
    "name": "St. Peter's Prep",
    "slug": "jersey-city-st-peters-prep"
  },
  {
    "id": "belmar-st-rose",
    "name": "St. Rose",
    "slug": "belmar-st-rose"
  },
  {
    "id": "edison-st-thomas-aquinas-formerly-bishop-ahr",
    "name": "St. Thomas Aquinas",
    "slug": "edison-st-thomas-aquinas-formerly-bishop-ahr"
  },
  {
    "id": "hamilton-steinert",
    "name": "Steinert",
    "slug": "hamilton-steinert"
  },
  {
    "id": "somerdale-sterling",
    "name": "Sterling",
    "slug": "somerdale-sterling"
  },
  {
    "id": "summit-summit",
    "name": "Summit",
    "slug": "summit-summit"
  },
  {
    "id": "teaneck-teaneck",
    "name": "Teaneck",
    "slug": "teaneck-teaneck"
  },
  {
    "id": "tenafly-tenafly",
    "name": "Tenafly",
    "slug": "tenafly-tenafly"
  },
  {
    "id": "erial-timber-creek",
    "name": "Timber Creek",
    "slug": "erial-timber-creek"
  },
  {
    "id": "toms-river-toms-river-east",
    "name": "Toms River East",
    "slug": "toms-river-toms-river-east"
  },
  {
    "id": "toms-river-toms-river-north",
    "name": "Toms River North",
    "slug": "toms-river-toms-river-north"
  },
  {
    "id": "toms-river-toms-river-south",
    "name": "Toms River South",
    "slug": "toms-river-toms-river-south"
  },
  {
    "id": "teaneck-torah-academy",
    "name": "Torah Academy",
    "slug": "teaneck-torah-academy"
  },
  {
    "id": "trenton-trenton",
    "name": "Trenton",
    "slug": "trenton-trenton"
  },
  {
    "id": "union-union",
    "name": "Union",
    "slug": "union-union"
  },
  {
    "id": "union-city-union-city",
    "name": "Union City",
    "slug": "union-city-union-city"
  },
  {
    "id": "vernon-vernon",
    "name": "Vernon",
    "slug": "vernon-vernon"
  },
  {
    "id": "verona-verona",
    "name": "Verona",
    "slug": "verona-verona"
  },
  {
    "id": "vineland-vineland",
    "name": "Vineland",
    "slug": "vineland-vineland"
  },
  {
    "id": "glen-gardner-voorhees",
    "name": "Voorhees",
    "slug": "glen-gardner-voorhees"
  },
  {
    "id": "waldwick-waldwick",
    "name": "Waldwick",
    "slug": "waldwick-waldwick"
  },
  {
    "id": "wall-wall",
    "name": "Wall",
    "slug": "wall-wall"
  },
  {
    "id": "hamburg-wallkill-valley",
    "name": "Wallkill Valley",
    "slug": "hamburg-wallkill-valley"
  },
  {
    "id": "washington-warren-hills",
    "name": "Warren Hills",
    "slug": "washington-warren-hills"
  },
  {
    "id": "sewell-washington-township",
    "name": "Washington Township",
    "slug": "sewell-washington-township"
  },
  {
    "id": "warren-watchung-hills",
    "name": "Watchung Hills",
    "slug": "warren-watchung-hills"
  },
  {
    "id": "wayne-wayne-hills",
    "name": "Wayne Hills",
    "slug": "wayne-wayne-hills"
  },
  {
    "id": "wayne-wayne-valley",
    "name": "Wayne Valley",
    "slug": "wayne-wayne-valley"
  },
  {
    "id": "weehawken-weehawken",
    "name": "Weehawken",
    "slug": "weehawken-weehawken"
  },
  {
    "id": "westville-west-deptford",
    "name": "West Deptford",
    "slug": "westville-west-deptford"
  },
  {
    "id": "north-caldwell-west-essex",
    "name": "West Essex",
    "slug": "north-caldwell-west-essex"
  },
  {
    "id": "west-milford-west-milford",
    "name": "West Milford",
    "slug": "west-milford-west-milford"
  },
  {
    "id": "chester-west-morris",
    "name": "West Morris",
    "slug": "chester-west-morris"
  },
  {
    "id": "west-orange-west-orange",
    "name": "West Orange",
    "slug": "west-orange-west-orange"
  },
  {
    "id": "plainsboro-west-windsor-plainsboro-north",
    "name": "West Windsor-Plainsboro North",
    "slug": "plainsboro-west-windsor-plainsboro-north"
  },
  {
    "id": "princeton-jct-west-windsor-plainsboro-south",
    "name": "West Windsor-Plainsboro South",
    "slug": "princeton-jct-west-windsor-plainsboro-south"
  },
  {
    "id": "westampton-westampton-tech",
    "name": "Westampton Tech",
    "slug": "westampton-westampton-tech"
  },
  {
    "id": "westfield-westfield",
    "name": "Westfield",
    "slug": "westfield-westfield"
  },
  {
    "id": "washington-twp-westwood",
    "name": "Westwood",
    "slug": "washington-twp-westwood"
  },
  {
    "id": "whippany-whippany-park",
    "name": "Whippany Park",
    "slug": "whippany-whippany-park"
  },
  {
    "id": "williamstown-williamstown",
    "name": "Williamstown",
    "slug": "williamstown-williamstown"
  },
  {
    "id": "willingboro-willingboro",
    "name": "Willingboro",
    "slug": "willingboro-willingboro"
  },
  {
    "id": "atco-winslow",
    "name": "Winslow",
    "slug": "atco-winslow"
  },
  {
    "id": "woodbridge-woodbridge",
    "name": "Woodbridge",
    "slug": "woodbridge-woodbridge"
  },
  {
    "id": "woodstown-woodstown",
    "name": "Woodstown",
    "slug": "woodstown-woodstown"
  }
]